damnik/__init__.py
damnik/hello.py
damnik-0.0.3.dist-info/METADATA
damnik-0.0.3.dist-info/WHEEL
damnik-0.0.3.dist-info/top_level.txt
damnik-0.0.3.dist-info/RECORD
