Metadata-Version: 2.1
Name: damnik
Version: 0.0.3
Summary: damnik package
Home-page: UNKNOWN
Author: Damnik Jain
Author-email: <damnikjain@gmail.com>
License: UNKNOWN
Keywords: python,video,stream,video stream,camera stream,sockets,damnik
Platform: UNKNOWN
Classifier: Development Status :: 1 - Planning
Classifier: Intended Audience :: Developers
Classifier: Programming Language :: Python :: 3
Classifier: Operating System :: Unix
Classifier: Operating System :: MacOS :: MacOS X
Classifier: Operating System :: Microsoft :: Windows
